drf_simplejwt_additions/__init__.py
drf_simplejwt_additions/middleware.py
drf_simplejwt_additions/serializers.py
drf_simplejwt_additions/views.py
drf_simplejwt_additions-1.1.3.dist-info/METADATA
drf_simplejwt_additions-1.1.3.dist-info/WHEEL
drf_simplejwt_additions-1.1.3.dist-info/top_level.txt
drf_simplejwt_additions-1.1.3.dist-info/RECORD
