Metadata-Version: 2.1
Name: drf-simplejwt-additions
Version: 1.1.3
Summary: Additions for Django Rest Framework Simple JWT
Home-page: https://github.com/AllYouZombies/drf-simplejwt-additions
Author: Astafeev Rustam
Author-email: rustam@astafeev.dev
License: MIT License
Classifier: Environment :: Web Environment
Classifier: Framework :: Django
Classifier: Framework :: Django :: 3.2
Classifier: Framework :: Django :: 4.0
Classifier: Framework :: Django :: 4.1
Classifier: Intended Audience :: Developers
Classifier: License :: OSI Approved :: MIT License
Classifier: Operating System :: OS Independent
Classifier: Programming Language :: Python
Classifier: Programming Language :: Python :: 3
Classifier: Programming Language :: Python :: 3.7
Classifier: Programming Language :: Python :: 3.8
Classifier: Programming Language :: Python :: 3.9
Classifier: Programming Language :: Python :: 3.10
Classifier: Programming Language :: Python :: 3.11
Classifier: Topic :: Internet :: WWW/HTTP
Classifier: Topic :: Internet :: WWW/HTTP :: Dynamic Content
Requires-Python: >=3.7
Requires-Dist: Django (>=3.2)
Requires-Dist: djangorestframework
Requires-Dist: djangorestframework-simplejwt
